{"implements":[],"javadoc":"Used by the CParser to handle fields added to structures(composites).\n Currently only bitfields are handled specially.\n \n NOTE: when bitfield handling is added directly to structures, this class may\n no longer be necessary.","static":false,"extends":"java.lang.Object","methods":[{"javadoc":"","static":false,"name":"<init>","comment":"","params":[{"type_long":"ghidra.program.model.data.Composite","name":"parent","comment":"","type_short":"Composite"}],"throws":[],"return":{"type_long":"void","comment":"","type_short":"void"}},{"javadoc":"","static":false,"name":"getComposite","comment":"","params":[],"throws":[],"return":{"type_long":"ghidra.program.model.data.Composite","comment":"","type_short":"Composite"}},{"javadoc":"","static":false,"name":"add","comment":"","params":[{"type_long":"ghidra.app.util.cparser.C.Declaration","name":"dec","comment":"","type_short":"Declaration"}],"throws":[{"type_long":"java.lang.IllegalArgumentException","comment":"","type_short":"IllegalArgumentException"}],"return":{"type_long":"void","comment":"","type_short":"void"}}],"name":"CompositeHandler","comment":"Used by the CParser to handle fields added to structures(composites).\n Currently only bitfields are handled specially.\n \n NOTE: when bitfield handling is added directly to structures, this class may\n no longer be necessary.","fields":[{"type_long":"ghidra.program.model.data.Composite","javadoc":"","static":false,"name":"parent","comment":"","type_short":"Composite","constant_value":null}]}
