{"implements":[],"javadoc":"Interface for listeners to format model changes.","static":false,"methods":[{"javadoc":"Notifies that a new format model was added to the format manager.\n@param model the new model.","static":false,"name":"formatModelAdded","comment":"Notifies that a new format model was added to the format manager.","params":[{"type_long":"ghidra.app.util.viewer.format.FieldFormatModel","name":"model","comment":"the new model.","type_short":"FieldFormatModel"}],"throws":[],"return":{"type_long":"void","comment":"","type_short":"void"}},{"javadoc":"Notifies that a format model was removed.\n@param model the model that was removed.","static":false,"name":"formatModelRemoved","comment":"Notifies that a format model was removed.","params":[{"type_long":"ghidra.app.util.viewer.format.FieldFormatModel","name":"model","comment":"the model that was removed.","type_short":"FieldFormatModel"}],"throws":[],"return":{"type_long":"void","comment":"","type_short":"void"}},{"javadoc":"Notifies that the given format model was changed.\n@param model the model that was changed.","static":false,"name":"formatModelChanged","comment":"Notifies that the given format model was changed.","params":[{"type_long":"ghidra.app.util.viewer.format.FieldFormatModel","name":"model","comment":"the model that was changed.","type_short":"FieldFormatModel"}],"throws":[],"return":{"type_long":"void","comment":"","type_short":"void"}}],"name":"FormatModelListener","comment":"Interface for listeners to format model changes.","fields":[]}
