{"implements":[],"javadoc":"Panel to show conflicts for properties and the number of conflicts.","static":false,"extends":"javax.swing.JPanel","methods":[{"javadoc":"","static":false,"name":"<init>","comment":"","params":[{"type_long":"ghidra.app.merge.ProgramMultiUserMergeManager","name":"mergeManager","comment":"","type_short":"ProgramMultiUserMergeManager"},{"type_long":"int","name":"totalConflicts","comment":"","type_short":"int"}],"throws":[],"return":{"type_long":"void","comment":"","type_short":"void"}},{"javadoc":"Update the panel with conflict information.\n@param info info to show conflict information\n@param conflictIndex conflict #n","static":false,"name":"setConflictInfo","comment":"Update the panel with conflict information.","params":[{"type_long":"int","name":"conflictIndex","comment":"conflict #n","type_short":"int"},{"type_long":"ghidra.app.merge.propertylist.ConflictInfo","name":"info","comment":"info to show conflict information","type_short":"ConflictInfo"}],"throws":[],"return":{"type_long":"void","comment":"","type_short":"void"}},{"javadoc":"","static":false,"name":"getSelectedOption","comment":"","params":[],"throws":[],"return":{"type_long":"int","comment":"","type_short":"int"}},{"javadoc":"","static":false,"name":"create","comment":"","params":[],"throws":[],"return":{"type_long":"void","comment":"","type_short":"void"}},{"javadoc":"","static":false,"name":"createConflictPanel","comment":"","params":[],"throws":[],"return":{"type_long":"ghidra.app.merge.propertylist.ConflictPanel","comment":"","type_short":"ConflictPanel"}},{"javadoc":"Selects or deselects the checkbox.\n@param useForAll true means select the checkbox.","static":false,"name":"setUseForAll","comment":"Selects or deselects the checkbox.","params":[{"type_long":"boolean","name":"useForAll","comment":"true means select the checkbox.","type_short":"boolean"}],"throws":[],"return":{"type_long":"void","comment":"","type_short":"void"}},{"javadoc":"Returns whether or not the checkbox is selected.\n@return true if the checkbox is selected.","static":false,"name":"getUseForAll","comment":"Returns whether or not the checkbox is selected.","params":[],"throws":[],"return":{"type_long":"boolean","comment":"true if the checkbox is selected.","type_short":"boolean"}}],"name":"PropertyListMergePanel","comment":"Panel to show conflicts for properties and the number of conflicts.","fields":[{"type_long":"java.lang.String","javadoc":"","static":true,"name":"LATEST_BUTTON_NAME","comment":"","type_short":"String","constant_value":"\"Latest\""},{"type_long":"java.lang.String","javadoc":"","static":true,"name":"CHECKED_OUT_BUTTON_NAME","comment":"","type_short":"String","constant_value":"\"Checked Out\""},{"type_long":"java.lang.String","javadoc":"","static":true,"name":"ORIGINAL_BUTTON_NAME","comment":"","type_short":"String","constant_value":"\"Original\""},{"type_long":"int","javadoc":"","static":false,"name":"totalConflicts","comment":"","type_short":"int","constant_value":null},{"type_long":"ghidra.app.merge.propertylist.ConflictPanel","javadoc":"","static":false,"name":"conflictPanel","comment":"","type_short":"ConflictPanel","constant_value":null},{"type_long":"ghidra.app.merge.util.ConflictCountPanel","javadoc":"","static":false,"name":"countPanel","comment":"","type_short":"ConflictCountPanel","constant_value":null},{"type_long":"ghidra.app.merge.ProgramMultiUserMergeManager","javadoc":"","static":false,"name":"mergeManager","comment":"","type_short":"ProgramMultiUserMergeManager","constant_value":null}]}
