{"implements":["ghidra.framework.store.FolderItem"],"javadoc":"<code>DataFileItem<\/code> corresponds to a private serialized\n data file within a FileSystem.  Methods are provided for opening\n the underlying file as an input or output stream.\n <br>\n NOTE: The use of DataFile is not encouraged and is not fully\n supported.","static":false,"methods":[{"javadoc":"Open the current version of this item for reading.\n@return input stream\n@throws FileNotFoundException","static":false,"name":"getInputStream","comment":"Open the current version of this item for reading.","params":[],"throws":[{"type_long":"java.io.FileNotFoundException","comment":"","type_short":"FileNotFoundException"}],"return":{"type_long":"java.io.InputStream","comment":"input stream","type_short":"InputStream"}},{"javadoc":"Open a new version of this item for writing.\n@return output stream.\n@throws FileNotFoundException","static":false,"name":"getOutputStream","comment":"Open a new version of this item for writing.","params":[],"throws":[{"type_long":"java.io.FileNotFoundException","comment":"","type_short":"FileNotFoundException"}],"return":{"type_long":"java.io.OutputStream","comment":"output stream.","type_short":"OutputStream"}},{"javadoc":"Open a specific version of this item for reading.\n@return input stream\n@throws FileNotFoundException","static":false,"name":"getInputStream","comment":"Open a specific version of this item for reading.","params":[{"type_long":"int","name":"version","comment":"","type_short":"int"}],"throws":[{"type_long":"java.io.FileNotFoundException","comment":"","type_short":"FileNotFoundException"}],"return":{"type_long":"java.io.InputStream","comment":"input stream","type_short":"InputStream"}}],"name":"DataFileItem","comment":"DataFileItem corresponds to a private serialized\n data file within a FileSystem.  Methods are provided for opening\n the underlying file as an input or output stream.\n \n NOTE: The use of DataFile is not encouraged and is not fully\n supported.","fields":[]}
