{"implements":[],"javadoc":"","static":false,"extends":"ghidra.program.util.ProgramLocation","methods":[{"javadoc":"","static":false,"name":"<init>","comment":"","params":[{"type_long":"ghidra.program.model.listing.Program","name":"program","comment":"","type_short":"Program"},{"type_long":"ghidra.program.model.address.Address","name":"addr","comment":"","type_short":"Address"},{"type_long":"int","name":"charOffset","comment":"","type_short":"int"}],"throws":[],"return":{"type_long":"void","comment":"","type_short":"void"}},{"javadoc":"","static":false,"name":"<init>","comment":"","params":[],"throws":[],"return":{"type_long":"void","comment":"","type_short":"void"}}],"name":"StackDepthFieldLocation","comment":"","fields":[]}
