{"implements":[],"javadoc":"A immutable hierarchical path based name implementation that can be viewed as either\n {@link Namespace namespaces} or {@link CategoryPath categorypaths}.\n <p>","static":false,"extends":"java.lang.Object","methods":[{"javadoc":"","static":true,"name":"createRoot","comment":"","params":[{"type_long":"ghidra.program.model.data.CategoryPath","name":"rootCategory","comment":"","type_short":"CategoryPath"}],"throws":[],"return":{"type_long":"ghidra.app.util.bin.format.dwarf4.next.DWARFNameInfo","comment":"","type_short":"DWARFNameInfo"}},{"javadoc":"","static":true,"name":"fromDataType","comment":"","params":[{"type_long":"ghidra.program.model.data.DataType","name":"dataType","comment":"","type_short":"DataType"}],"throws":[],"return":{"type_long":"ghidra.app.util.bin.format.dwarf4.next.DWARFNameInfo","comment":"","type_short":"DWARFNameInfo"}},{"javadoc":"","static":true,"name":"fromList","comment":"","params":[{"type_long":"ghidra.app.util.bin.format.dwarf4.next.DWARFNameInfo","name":"parent","comment":"","type_short":"DWARFNameInfo"},{"type_long":"java.util.List<java.lang.String>","name":"names","comment":"","type_short":"List"}],"throws":[],"return":{"type_long":"ghidra.app.util.bin.format.dwarf4.next.DWARFNameInfo","comment":"","type_short":"DWARFNameInfo"}},{"javadoc":"","static":false,"name":"<init>","comment":"","params":[{"type_long":"ghidra.app.util.bin.format.dwarf4.next.DWARFNameInfo","name":"parent","comment":"","type_short":"DWARFNameInfo"},{"type_long":"ghidra.program.model.data.CategoryPath","name":"organizationalCategoryPath","comment":"","type_short":"CategoryPath"},{"type_long":"ghidra.app.util.bin.format.dwarf4.next.NamespacePath","name":"namespacePath","comment":"","type_short":"NamespacePath"},{"type_long":"java.lang.String","name":"originalName","comment":"","type_short":"String"}],"throws":[],"return":{"type_long":"void","comment":"","type_short":"void"}},{"javadoc":"","static":false,"name":"<init>","comment":"","params":[{"type_long":"ghidra.app.util.bin.format.dwarf4.next.DWARFNameInfo","name":"parent","comment":"","type_short":"DWARFNameInfo"},{"type_long":"java.lang.String","name":"originalName","comment":"","type_short":"String"},{"type_long":"java.lang.String","name":"name","comment":"","type_short":"String"},{"type_long":"ghidra.program.model.symbol.SymbolType","name":"type","comment":"","type_short":"SymbolType"}],"throws":[],"return":{"type_long":"void","comment":"","type_short":"void"}},{"javadoc":"","static":false,"name":"getParent","comment":"","params":[],"throws":[],"return":{"type_long":"ghidra.app.util.bin.format.dwarf4.next.DWARFNameInfo","comment":"","type_short":"DWARFNameInfo"}},{"javadoc":"","static":false,"name":"isRoot","comment":"","params":[],"throws":[],"return":{"type_long":"boolean","comment":"","type_short":"boolean"}},{"javadoc":"","static":false,"name":"getOrganizationalCategoryPath","comment":"","params":[],"throws":[],"return":{"type_long":"ghidra.program.model.data.CategoryPath","comment":"","type_short":"CategoryPath"}},{"javadoc":"","static":false,"name":"getNamespacePath","comment":"","params":[],"throws":[],"return":{"type_long":"ghidra.app.util.bin.format.dwarf4.next.NamespacePath","comment":"","type_short":"NamespacePath"}},{"javadoc":"","static":false,"name":"getParentCP","comment":"","params":[],"throws":[],"return":{"type_long":"ghidra.program.model.data.CategoryPath","comment":"","type_short":"CategoryPath"}},{"javadoc":"","static":false,"name":"getName","comment":"","params":[],"throws":[],"return":{"type_long":"java.lang.String","comment":"","type_short":"String"}},{"javadoc":"","static":false,"name":"replaceName","comment":"","params":[{"type_long":"java.lang.String","name":"newName","comment":"","type_short":"String"},{"type_long":"java.lang.String","name":"newOriginalName","comment":"","type_short":"String"}],"throws":[],"return":{"type_long":"ghidra.app.util.bin.format.dwarf4.next.DWARFNameInfo","comment":"","type_short":"DWARFNameInfo"}},{"javadoc":"","static":false,"name":"replaceType","comment":"","params":[{"type_long":"ghidra.program.model.symbol.SymbolType","name":"newType","comment":"","type_short":"SymbolType"}],"throws":[],"return":{"type_long":"ghidra.app.util.bin.format.dwarf4.next.DWARFNameInfo","comment":"","type_short":"DWARFNameInfo"}},{"javadoc":"","static":false,"name":"getType","comment":"","params":[],"throws":[],"return":{"type_long":"ghidra.program.model.symbol.SymbolType","comment":"","type_short":"SymbolType"}},{"javadoc":"Converts this object into an equiv {@link CategoryPath}.\n@return {@link CategoryPath}: \"\/organizational_cat_path\/namespace1\/namespace2\/obj_name\"","static":false,"name":"asCategoryPath","comment":"Converts this object into an equiv CategoryPath.","params":[],"throws":[],"return":{"type_long":"ghidra.program.model.data.CategoryPath","comment":"CategoryPath: \"\/organizational_cat_path\/namespace1\/namespace2\/obj_name\"","type_short":"CategoryPath"}},{"javadoc":"Converts this object into an equiv {@link DataTypePath}.\n@return {@link DataTypePath}: { \"\/organizational_cat_path\/namespace1\/namespace2\", \"obj_name\" }","static":false,"name":"asDataTypePath","comment":"Converts this object into an equiv DataTypePath.","params":[],"throws":[],"return":{"type_long":"ghidra.program.model.data.DataTypePath","comment":"DataTypePath: { \"\/organizational_cat_path\/namespace1\/namespace2\", \"obj_name\" }","type_short":"DataTypePath"}},{"javadoc":"","static":false,"name":"getParentNamespace","comment":"","params":[{"type_long":"ghidra.program.model.listing.Program","name":"program","comment":"","type_short":"Program"}],"throws":[],"return":{"type_long":"ghidra.program.model.symbol.Namespace","comment":"","type_short":"Namespace"}},{"javadoc":"Converts this object into an equiv Ghidra {@link Namespace}, omitting the organizational\n category path (which only applies to DataTypes).\n@param program {@link Program} where the namespace lives.\n@return {@link Namespace}: \"ROOT::namespace1::namespace2::obj_name\"","static":false,"name":"asNamespace","comment":"Converts this object into an equiv Ghidra Namespace, omitting the organizational\n category path (which only applies to DataTypes).","params":[{"type_long":"ghidra.program.model.listing.Program","name":"program","comment":"Program where the namespace lives.","type_short":"Program"}],"throws":[],"return":{"type_long":"ghidra.program.model.symbol.Namespace","comment":"Namespace: \"ROOT::namespace1::namespace2::obj_name\"","type_short":"Namespace"}},{"javadoc":"","static":false,"name":"toString","comment":"","params":[],"throws":[],"return":{"type_long":"java.lang.String","comment":"","type_short":"String"}},{"javadoc":"","static":false,"name":"isAnon","comment":"","params":[],"throws":[],"return":{"type_long":"boolean","comment":"","type_short":"boolean"}},{"javadoc":"","static":false,"name":"getOriginalName","comment":"","params":[],"throws":[],"return":{"type_long":"java.lang.String","comment":"","type_short":"String"}},{"javadoc":"Returns true if this instance's {@link #getName() name} value is different\n than its {@link #getOriginalName() original} form.\n <p>\n@return ","static":false,"name":"isNameModified","comment":"Returns true if this instance's #getName() value is different\n than its #getOriginalName() form.\n ","params":[],"throws":[],"return":{"type_long":"boolean","comment":"","type_short":"boolean"}},{"javadoc":"","static":false,"name":"createChild","comment":"","params":[{"type_long":"java.lang.String","name":"childOriginalName","comment":"","type_short":"String"},{"type_long":"java.lang.String","name":"childName","comment":"","type_short":"String"},{"type_long":"ghidra.program.model.symbol.SymbolType","name":"childType","comment":"","type_short":"SymbolType"}],"throws":[],"return":{"type_long":"ghidra.app.util.bin.format.dwarf4.next.DWARFNameInfo","comment":"","type_short":"DWARFNameInfo"}},{"javadoc":"","static":false,"name":"hashCode","comment":"","params":[],"throws":[],"return":{"type_long":"int","comment":"","type_short":"int"}},{"javadoc":"","static":false,"name":"equals","comment":"","params":[{"type_long":"java.lang.Object","name":"obj","comment":"","type_short":"Object"}],"throws":[],"return":{"type_long":"boolean","comment":"","type_short":"boolean"}}],"name":"DWARFNameInfo","comment":"A immutable hierarchical path based name implementation that can be viewed as either\n Namespace or CategoryPath.\n ","fields":[{"type_long":"ghidra.app.util.bin.format.dwarf4.next.DWARFNameInfo","javadoc":"","static":false,"name":"parent","comment":"","type_short":"DWARFNameInfo","constant_value":null},{"type_long":"ghidra.program.model.data.CategoryPath","javadoc":"","static":false,"name":"organizationalCategoryPath","comment":"","type_short":"CategoryPath","constant_value":null},{"type_long":"ghidra.app.util.bin.format.dwarf4.next.NamespacePath","javadoc":"","static":false,"name":"namespacePath","comment":"","type_short":"NamespacePath","constant_value":null},{"type_long":"java.lang.String","javadoc":"","static":false,"name":"originalName","comment":"","type_short":"String","constant_value":null}]}
