{"implements":[],"javadoc":"Interface for classes that will handle drop actions for {@link DataTree}s.","static":false,"methods":[{"javadoc":"","static":false,"name":"handle","comment":"","params":[{"type_long":"ghidra.framework.plugintool.PluginTool","name":"tool","comment":"","type_short":"PluginTool"},{"type_long":"ghidra.framework.main.datatree.DataTree","name":"dataTree","comment":"","type_short":"DataTree"},{"type_long":"docking.widgets.tree.GTreeNode","name":"destinationNode","comment":"","type_short":"GTreeNode"},{"type_long":"java.lang.Object","name":"transferData","comment":"","type_short":"Object"},{"type_long":"int","name":"dropAction","comment":"","type_short":"int"}],"throws":[],"return":{"type_long":"void","comment":"","type_short":"void"}}],"name":"DataTreeFlavorHandler","comment":"Interface for classes that will handle drop actions for DataTrees.","fields":[]}
