{"implements":[],"javadoc":"Exception thrown if there was a problem accessing an Option, or if\n an informational message is to be conveyed.","static":false,"extends":"java.lang.Exception","methods":[{"javadoc":"Construct a new OptionException.\n@param msg reason for the exception","static":false,"name":"<init>","comment":"Construct a new OptionException.","params":[{"type_long":"java.lang.String","name":"msg","comment":"reason for the exception","type_short":"String"}],"throws":[],"return":{"type_long":"void","comment":"","type_short":"void"}},{"javadoc":"Construct a new OptionException that may be an informational message\n if isValid is true.\n@param msg message to display\n@param isInfo true if the msg is in informational message","static":false,"name":"<init>","comment":"Construct a new OptionException that may be an informational message\n if isValid is true.","params":[{"type_long":"java.lang.String","name":"msg","comment":"message to display","type_short":"String"},{"type_long":"boolean","name":"isInfo","comment":"true if the msg is in informational message","type_short":"boolean"}],"throws":[],"return":{"type_long":"void","comment":"","type_short":"void"}},{"javadoc":"Return whether the message associated with this exception is\n informational.","static":false,"name":"isInfoMessage","comment":"Return whether the message associated with this exception is\n informational.","params":[],"throws":[],"return":{"type_long":"boolean","comment":"","type_short":"boolean"}}],"name":"OptionException","comment":"Exception thrown if there was a problem accessing an Option, or if\n an informational message is to be conveyed.","fields":[{"type_long":"boolean","javadoc":"","static":false,"name":"isInfo","comment":"","type_short":"boolean","constant_value":null}]}
