{"implements":["ghidra.util.bean.GGlassPanePainter"],"javadoc":"A class that paints a given image with varying zoom levels.  The zoom is set by clients \n according to changes made by an {@link org.jdesktop.animation.timing.Animator}.  In essence, \n this class paints the given image centered over the given target bounds at some \n level of zoom.  If the zoom or bounds of the parent container are never changed, \n then the image painted by this class will not change.\n <p>\n NOTE: This class and it's getters\/setters need to be public for reflective callbacks","static":false,"extends":"java.lang.Object","methods":[{"javadoc":"","static":false,"name":"<init>","comment":"","params":[{"type_long":"java.awt.Rectangle","name":"targetBounds","comment":"","type_short":"Rectangle"},{"type_long":"java.awt.Image","name":"image","comment":"","type_short":"Image"}],"throws":[],"return":{"type_long":"void","comment":"","type_short":"void"}},{"javadoc":"","static":false,"name":"paint","comment":"","params":[{"type_long":"ghidra.util.bean.GGlassPane","name":"glassPane","comment":"","type_short":"GGlassPane"},{"type_long":"java.awt.Graphics","name":"g","comment":"","type_short":"Graphics"}],"throws":[],"return":{"type_long":"void","comment":"","type_short":"void"}},{"javadoc":"","static":false,"name":"getZoom","comment":"","params":[],"throws":[],"return":{"type_long":"float","comment":"","type_short":"float"}},{"javadoc":"","static":false,"name":"setZoom","comment":"","params":[{"type_long":"float","name":"zoom","comment":"","type_short":"float"}],"throws":[],"return":{"type_long":"void","comment":"","type_short":"void"}},{"javadoc":"","static":false,"name":"getTargetBounds","comment":"","params":[],"throws":[],"return":{"type_long":"java.awt.Rectangle","comment":"","type_short":"Rectangle"}},{"javadoc":"","static":false,"name":"setTargetBounds","comment":"","params":[{"type_long":"java.awt.Rectangle","name":"containerBounds","comment":"","type_short":"Rectangle"}],"throws":[],"return":{"type_long":"void","comment":"","type_short":"void"}},{"javadoc":"","static":false,"name":"setMagnifyFactor","comment":"","params":[{"type_long":"float","name":"factor","comment":"","type_short":"float"}],"throws":[],"return":{"type_long":"void","comment":"","type_short":"void"}},{"javadoc":"","static":true,"name":"createIconImage","comment":"","params":[{"type_long":"javax.swing.Icon","name":"icon","comment":"","type_short":"Icon"}],"throws":[],"return":{"type_long":"java.awt.Image","comment":"","type_short":"Image"}}],"name":"ZoomedImagePainter","comment":"A class that paints a given image with varying zoom levels.  The zoom is set by clients \n according to changes made by an org.jdesktop.animation.timing.Animator.  In essence, \n this class paints the given image centered over the given target bounds at some \n level of zoom.  If the zoom or bounds of the parent container are never changed, \n then the image painted by this class will not change.\n \n NOTE: This class and it's getters\/setters need to be public for reflective callbacks","fields":[{"type_long":"java.awt.Rectangle","javadoc":"","static":false,"name":"targetBounds","comment":"","type_short":"Rectangle","constant_value":null},{"type_long":"java.awt.Image","javadoc":"","static":false,"name":"image","comment":"","type_short":"Image","constant_value":null},{"type_long":"float","javadoc":"","static":false,"name":"zoom","comment":"","type_short":"float","constant_value":null},{"type_long":"float","javadoc":"","static":false,"name":"magnifyFactor","comment":"","type_short":"float","constant_value":null}]}
