{"implements":[],"javadoc":"Generates pre-comment fields.","static":false,"extends":"ghidra.app.util.viewer.field.FieldFactory","methods":[{"javadoc":"Constructor","static":false,"name":"<init>","comment":"Constructor","params":[],"throws":[],"return":{"type_long":"void","comment":"","type_short":"void"}},{"javadoc":"Constructor\n@param model the model that the field belongs to.\n@param hlProvider the HightLightStringProvider.\n@param displayOptions the Options for display properties.\n@param fieldOptions the Options for field specific properties.","static":false,"name":"<init>","comment":"Constructor","params":[{"type_long":"ghidra.app.util.viewer.format.FieldFormatModel","name":"model","comment":"the model that the field belongs to.","type_short":"FieldFormatModel"},{"type_long":"ghidra.app.util.HighlightProvider","name":"hlProvider","comment":"the HightLightStringProvider.","type_short":"HighlightProvider"},{"type_long":"ghidra.framework.options.Options","name":"displayOptions","comment":"the Options for display properties.","type_short":"Options"},{"type_long":"ghidra.framework.options.Options","name":"fieldOptions","comment":"the Options for field specific properties.","type_short":"Options"}],"throws":[],"return":{"type_long":"void","comment":"","type_short":"void"}},{"javadoc":"","static":false,"name":"getField","comment":"","params":[{"type_long":"ghidra.app.util.viewer.proxy.ProxyObj<?>","name":"proxy","comment":"","type_short":"ProxyObj"},{"type_long":"int","name":"varWidth","comment":"","type_short":"int"}],"throws":[],"return":{"type_long":"ghidra.app.util.viewer.field.ListingField","comment":"","type_short":"ListingField"}},{"javadoc":"","static":false,"name":"getDefinedPreComments","comment":"","params":[{"type_long":"ghidra.program.model.listing.CodeUnit","name":"cu","comment":"","type_short":"CodeUnit"}],"throws":[],"return":{"type_long":"java.lang.String[]","comment":"","type_short":"java.lang.String[]"}},{"javadoc":"","static":false,"name":"getAutoPreComments","comment":"","params":[{"type_long":"ghidra.program.model.listing.CodeUnit","name":"cu","comment":"","type_short":"CodeUnit"}],"throws":[],"return":{"type_long":"java.lang.String[]","comment":"","type_short":"java.lang.String[]"}},{"javadoc":"","static":false,"name":"getProgramLocation","comment":"","params":[{"type_long":"int","name":"row","comment":"","type_short":"int"},{"type_long":"int","name":"col","comment":"","type_short":"int"},{"type_long":"ghidra.app.util.viewer.field.ListingField","name":"bf","comment":"","type_short":"ListingField"}],"throws":[],"return":{"type_long":"ghidra.program.util.ProgramLocation","comment":"","type_short":"ProgramLocation"}},{"javadoc":"","static":false,"name":"getFieldLocation","comment":"","params":[{"type_long":"ghidra.app.util.viewer.field.ListingField","name":"bf","comment":"","type_short":"ListingField"},{"type_long":"java.math.BigInteger","name":"index","comment":"","type_short":"BigInteger"},{"type_long":"int","name":"fieldNum","comment":"","type_short":"int"},{"type_long":"ghidra.program.util.ProgramLocation","name":"programLoc","comment":"","type_short":"ProgramLocation"}],"throws":[],"return":{"type_long":"docking.widgets.fieldpanel.support.FieldLocation","comment":"","type_short":"FieldLocation"}},{"javadoc":"","static":false,"name":"acceptsType","comment":"","params":[{"type_long":"int","name":"category","comment":"","type_short":"int"},{"type_long":"java.lang.Class<?>","name":"proxyObjectClass","comment":"","type_short":"Class"}],"throws":[],"return":{"type_long":"boolean","comment":"","type_short":"boolean"}},{"javadoc":"","static":false,"name":"newInstance","comment":"","params":[{"type_long":"ghidra.app.util.viewer.format.FieldFormatModel","name":"formatModel","comment":"","type_short":"FieldFormatModel"},{"type_long":"ghidra.app.util.HighlightProvider","name":"provider","comment":"","type_short":"HighlightProvider"},{"type_long":"ghidra.framework.options.ToolOptions","name":"toolOptions","comment":"","type_short":"ToolOptions"},{"type_long":"ghidra.framework.options.ToolOptions","name":"fieldOptions","comment":"","type_short":"ToolOptions"}],"throws":[],"return":{"type_long":"ghidra.app.util.viewer.field.FieldFactory","comment":"","type_short":"FieldFactory"}},{"javadoc":"","static":false,"name":"getDefaultColor","comment":"","params":[],"throws":[],"return":{"type_long":"java.awt.Color","comment":"","type_short":"Color"}},{"javadoc":"","static":false,"name":"fieldOptionsChanged","comment":"","params":[{"type_long":"ghidra.framework.options.Options","name":"options","comment":"","type_short":"Options"},{"type_long":"java.lang.String","name":"optionName","comment":"","type_short":"String"},{"type_long":"java.lang.Object","name":"oldValue","comment":"","type_short":"Object"},{"type_long":"java.lang.Object","name":"newValue","comment":"","type_short":"Object"}],"throws":[],"return":{"type_long":"void","comment":"","type_short":"void"}},{"javadoc":"","static":false,"name":"getInstructionAutoComments","comment":"","params":[{"type_long":"ghidra.program.model.listing.Instruction","name":"instr","comment":"","type_short":"Instruction"}],"throws":[],"return":{"type_long":"java.lang.String[]","comment":"","type_short":"java.lang.String[]"}},{"javadoc":"","static":false,"name":"getDataAutoComments","comment":"","params":[{"type_long":"ghidra.program.model.listing.Data","name":"data","comment":"","type_short":"Data"}],"throws":[],"return":{"type_long":"java.lang.String[]","comment":"","type_short":"java.lang.String[]"}},{"javadoc":"","static":false,"name":"getFlexArrayComment","comment":"","params":[{"type_long":"ghidra.program.model.listing.Data","name":"data","comment":"","type_short":"Data"},{"type_long":"ghidra.program.model.address.Address","name":"addr","comment":"","type_short":"Address"}],"throws":[],"return":{"type_long":"java.lang.String[]","comment":"","type_short":"java.lang.String[]"}},{"javadoc":"","static":false,"name":"buildFlexArrayComment","comment":"","params":[{"type_long":"ghidra.program.model.listing.Data","name":"data","comment":"","type_short":"Data"},{"type_long":"int","name":"levelsToIgnore","comment":"","type_short":"int"},{"type_long":"java.lang.String","name":"label","comment":"","type_short":"String"}],"throws":[],"return":{"type_long":"java.lang.String[]","comment":"","type_short":"java.lang.String[]"}},{"javadoc":"","static":false,"name":"getTextField","comment":"","params":[{"type_long":"java.lang.String[]","name":"comments","comment":"","type_short":"java.lang.String[]"},{"type_long":"java.lang.String[]","name":"autoComment","comment":"","type_short":"java.lang.String[]"},{"type_long":"ghidra.app.util.viewer.proxy.ProxyObj<?>","name":"proxy","comment":"","type_short":"ProxyObj"},{"type_long":"int","name":"xStart","comment":"","type_short":"int"}],"throws":[],"return":{"type_long":"ghidra.app.util.viewer.field.ListingTextField","comment":"","type_short":"ListingTextField"}},{"javadoc":"","static":false,"name":"init","comment":"","params":[{"type_long":"ghidra.framework.options.Options","name":"options","comment":"","type_short":"Options"}],"throws":[],"return":{"type_long":"void","comment":"","type_short":"void"}}],"name":"PreCommentFieldFactory","comment":"Generates pre-comment fields.","fields":[{"type_long":"java.lang.String[]","javadoc":"","static":true,"name":"EMPTY_STRING_ARRAY","comment":"","type_short":"java.lang.String[]","constant_value":null},{"type_long":"java.lang.String","javadoc":"","static":true,"name":"FIELD_NAME","comment":"","type_short":"String","constant_value":"\"Pre-Comment\""},{"type_long":"java.lang.String","javadoc":"","static":true,"name":"GROUP_TITLE","comment":"","type_short":"String","constant_value":"\"Format Code\""},{"type_long":"java.lang.String","javadoc":"","static":true,"name":"FIELD_GROUP_TITLE","comment":"","type_short":"String","constant_value":"\"Pre-comments Field\""},{"type_long":"java.lang.String","javadoc":"","static":true,"name":"ENABLE_WORD_WRAP_MSG","comment":"","type_short":"String","constant_value":"\"Pre-comments Field.Enable Word Wrapping\""},{"type_long":"java.lang.String","javadoc":"","static":true,"name":"ENABLE_ALWAYS_SHOW_AUTOMATIC_MSG","comment":"","type_short":"String","constant_value":"\"Pre-comments Field.Always Show the Automatic Comment\""},{"type_long":"java.lang.String","javadoc":"","static":true,"name":"FLAG_FUNCTION_ENTRY_OPTION","comment":"","type_short":"String","constant_value":"\"Format Code.Flag Function Entry\""},{"type_long":"java.lang.String","javadoc":"","static":true,"name":"FLAG_SUBROUTINE_ENTRY_OPTION","comment":"","type_short":"String","constant_value":"\"Format Code.Flag Subroutine Entry\""},{"type_long":"java.lang.String","javadoc":"","static":true,"name":"FUNCTION_FLAG_COMMENT","comment":"","type_short":"String","constant_value":null},{"type_long":"java.lang.String","javadoc":"","static":true,"name":"SUBROUTINE_FLAG_COMMENT","comment":"","type_short":"String","constant_value":null},{"type_long":"boolean","javadoc":"","static":false,"name":"flagFunctionEntry","comment":"","type_short":"boolean","constant_value":null},{"type_long":"boolean","javadoc":"","static":false,"name":"flagSubroutineEntry","comment":"","type_short":"boolean","constant_value":null},{"type_long":"boolean","javadoc":"","static":false,"name":"isWordWrap","comment":"","type_short":"boolean","constant_value":null},{"type_long":"boolean","javadoc":"","static":false,"name":"alwaysShowAutomatic","comment":"","type_short":"boolean","constant_value":null},{"type_long":"java.awt.Color","javadoc":"","static":false,"name":"automaticCommentColor","comment":"","type_short":"Color","constant_value":null},{"type_long":"int","javadoc":"","static":false,"name":"automaticCommentStyle","comment":"","type_short":"int","constant_value":null}]}
