{"implements":[],"javadoc":"Represents a _STRUCT_X86_THREAD_STATE64 structure.\n@see <a href=\"https:\/\/opensource.apple.com\/source\/xnu\/xnu-4570.71.2\/osfmk\/mach\/i386\/_structs.h.auto.html\">mach\/i386\/_structs.h<\/a>","static":false,"extends":"ghidra.app.util.bin.format.macho.threadcommand.ThreadStateX86","methods":[{"javadoc":"","static":true,"name":"createThreadStateX86_64","comment":"","params":[{"type_long":"ghidra.app.util.bin.format.FactoryBundledWithBinaryReader","name":"reader","comment":"","type_short":"FactoryBundledWithBinaryReader"}],"throws":[{"type_long":"java.io.IOException","comment":"","type_short":"IOException"}],"return":{"type_long":"ghidra.app.util.bin.format.macho.threadcommand.ThreadStateX86_64","comment":"","type_short":"ThreadStateX86_64"}},{"javadoc":"DO NOT USE THIS CONSTRUCTOR, USE create*(GenericFactory ...) FACTORY METHODS INSTEAD.","static":false,"name":"<init>","comment":"DO NOT USE THIS CONSTRUCTOR, USE create*(GenericFactory ...) FACTORY METHODS INSTEAD.","params":[],"throws":[],"return":{"type_long":"void","comment":"","type_short":"void"}},{"javadoc":"","static":false,"name":"initThreadStateX86_64","comment":"","params":[{"type_long":"ghidra.app.util.bin.format.FactoryBundledWithBinaryReader","name":"reader","comment":"","type_short":"FactoryBundledWithBinaryReader"}],"throws":[{"type_long":"java.io.IOException","comment":"","type_short":"IOException"}],"return":{"type_long":"void","comment":"","type_short":"void"}},{"javadoc":"","static":false,"name":"getInstructionPointer","comment":"","params":[],"throws":[],"return":{"type_long":"long","comment":"","type_short":"long"}},{"javadoc":"","static":false,"name":"toDataType","comment":"","params":[],"throws":[{"type_long":"ghidra.util.exception.DuplicateNameException","comment":"","type_short":"DuplicateNameException"},{"type_long":"java.io.IOException","comment":"","type_short":"IOException"}],"return":{"type_long":"ghidra.program.model.data.DataType","comment":"","type_short":"DataType"}}],"name":"ThreadStateX86_64","comment":"Represents a _STRUCT_X86_THREAD_STATE64 structure.","fields":[{"type_long":"long","javadoc":"","static":false,"name":"rax","comment":"","type_short":"long","constant_value":null},{"type_long":"long","javadoc":"","static":false,"name":"rbx","comment":"","type_short":"long","constant_value":null},{"type_long":"long","javadoc":"","static":false,"name":"rcx","comment":"","type_short":"long","constant_value":null},{"type_long":"long","javadoc":"","static":false,"name":"rdx","comment":"","type_short":"long","constant_value":null},{"type_long":"long","javadoc":"","static":false,"name":"rdi","comment":"","type_short":"long","constant_value":null},{"type_long":"long","javadoc":"","static":false,"name":"rsi","comment":"","type_short":"long","constant_value":null},{"type_long":"long","javadoc":"","static":false,"name":"rbp","comment":"","type_short":"long","constant_value":null},{"type_long":"long","javadoc":"","static":false,"name":"rsp","comment":"","type_short":"long","constant_value":null},{"type_long":"long","javadoc":"","static":false,"name":"r8","comment":"","type_short":"long","constant_value":null},{"type_long":"long","javadoc":"","static":false,"name":"r9","comment":"","type_short":"long","constant_value":null},{"type_long":"long","javadoc":"","static":false,"name":"r10","comment":"","type_short":"long","constant_value":null},{"type_long":"long","javadoc":"","static":false,"name":"r11","comment":"","type_short":"long","constant_value":null},{"type_long":"long","javadoc":"","static":false,"name":"r12","comment":"","type_short":"long","constant_value":null},{"type_long":"long","javadoc":"","static":false,"name":"r13","comment":"","type_short":"long","constant_value":null},{"type_long":"long","javadoc":"","static":false,"name":"r14","comment":"","type_short":"long","constant_value":null},{"type_long":"long","javadoc":"","static":false,"name":"r15","comment":"","type_short":"long","constant_value":null},{"type_long":"long","javadoc":"","static":false,"name":"rip","comment":"","type_short":"long","constant_value":null},{"type_long":"long","javadoc":"","static":false,"name":"rflags","comment":"","type_short":"long","constant_value":null},{"type_long":"long","javadoc":"","static":false,"name":"cs","comment":"","type_short":"long","constant_value":null},{"type_long":"long","javadoc":"","static":false,"name":"fs","comment":"","type_short":"long","constant_value":null},{"type_long":"long","javadoc":"","static":false,"name":"gs","comment":"","type_short":"long","constant_value":null}]}
