{"implements":[],"javadoc":"","static":false,"extends":"java.lang.Object","methods":[{"javadoc":"","static":false,"name":"<init>","comment":"","params":[{"type_long":"help.validator.location.HelpModuleLocation","name":"help","comment":"","type_short":"HelpModuleLocation"},{"type_long":"java.nio.file.Path","name":"file","comment":"","type_short":"Path"}],"throws":[],"return":{"type_long":"void","comment":"","type_short":"void"}},{"javadoc":"","static":false,"name":"cleanupHelpFile","comment":"","params":[],"throws":[],"return":{"type_long":"void","comment":"","type_short":"void"}},{"javadoc":"","static":false,"name":"getAllHREFs","comment":"","params":[],"throws":[],"return":{"type_long":"java.util.Collection<help.validator.model.HREF>","comment":"","type_short":"Collection"}},{"javadoc":"","static":false,"name":"getAllIMGs","comment":"","params":[],"throws":[],"return":{"type_long":"java.util.Collection<help.validator.model.IMG>","comment":"","type_short":"Collection"}},{"javadoc":"","static":false,"name":"getRelativePath","comment":"","params":[],"throws":[],"return":{"type_long":"java.nio.file.Path","comment":"","type_short":"Path"}},{"javadoc":"","static":false,"name":"containsAnchor","comment":"","params":[{"type_long":"java.lang.String","name":"anchorName","comment":"","type_short":"String"}],"throws":[],"return":{"type_long":"boolean","comment":"","type_short":"boolean"}},{"javadoc":"","static":false,"name":"getDuplicateAnchorsByID","comment":"","params":[],"throws":[],"return":{"type_long":"java.util.Map<java.lang.String,java.util.List<help.validator.model.AnchorDefinition>>","comment":"","type_short":"Map"}},{"javadoc":"","static":false,"name":"getAnchorDefinition","comment":"","params":[{"type_long":"java.nio.file.Path","name":"helpPath","comment":"","type_short":"Path"}],"throws":[],"return":{"type_long":"help.validator.model.AnchorDefinition","comment":"","type_short":"AnchorDefinition"}},{"javadoc":"","static":false,"name":"getAllAnchorDefinitions","comment":"","params":[],"throws":[],"return":{"type_long":"java.util.Collection<help.validator.model.AnchorDefinition>","comment":"","type_short":"Collection"}},{"javadoc":"","static":false,"name":"getFile","comment":"","params":[],"throws":[],"return":{"type_long":"java.nio.file.Path","comment":"","type_short":"Path"}},{"javadoc":"","static":false,"name":"toString","comment":"","params":[],"throws":[],"return":{"type_long":"java.lang.String","comment":"","type_short":"String"}},{"javadoc":"","static":false,"name":"parseLinks","comment":"","params":[],"throws":[],"return":{"type_long":"void","comment":"","type_short":"void"}},{"javadoc":"","static":true,"name":"processHelpFile","comment":"","params":[{"type_long":"java.nio.file.Path","name":"file","comment":"","type_short":"Path"},{"type_long":"help.validator.AnchorManager","name":"anchorManager","comment":"","type_short":"AnchorManager"},{"type_long":"help.validator.TagProcessor","name":"tagProcessor","comment":"","type_short":"TagProcessor"}],"throws":[],"return":{"type_long":"void","comment":"","type_short":"void"}}],"name":"HelpFile","comment":"","fields":[{"type_long":"java.nio.file.Path","javadoc":"","static":false,"name":"helpFile","comment":"","type_short":"Path","constant_value":null},{"type_long":"help.validator.location.HelpModuleLocation","javadoc":"","static":false,"name":"help","comment":"","type_short":"HelpModuleLocation","constant_value":null},{"type_long":"java.nio.file.Path","javadoc":"","static":false,"name":"relativePath","comment":"","type_short":"Path","constant_value":null},{"type_long":"help.validator.AnchorManager","javadoc":"","static":false,"name":"anchorManager","comment":"","type_short":"AnchorManager","constant_value":null}]}
