{"implements":[],"javadoc":"","static":false,"extends":"java.lang.Object","methods":[{"javadoc":"","static":false,"name":"<init>","comment":"","params":[{"type_long":"int","name":"address","comment":"","type_short":"int"},{"type_long":"java.lang.String","name":"cmt","comment":"","type_short":"String"},{"type_long":"java.lang.String","name":"dll","comment":"","type_short":"String"},{"type_long":"java.lang.String","name":"name","comment":"","type_short":"String"},{"type_long":"boolean","name":"isBound","comment":"","type_short":"boolean"}],"throws":[],"return":{"type_long":"void","comment":"","type_short":"void"}},{"javadoc":"Returns the adjusted address where the import occurs.\n@return the adjusted address where the import occurs","static":false,"name":"getAddress","comment":"Returns the adjusted address where the import occurs.","params":[],"throws":[],"return":{"type_long":"int","comment":"the adjusted address where the import occurs","type_short":"int"}},{"javadoc":"Returns a comment string containing extra information about the import.\n@return a comment string containing extra information about the import","static":false,"name":"getComment","comment":"Returns a comment string containing extra information about the import.","params":[],"throws":[],"return":{"type_long":"java.lang.String","comment":"a comment string containing extra information about the import","type_short":"String"}},{"javadoc":"Returns the name of the imported DLL.\n@return the name of the imported DLL","static":false,"name":"getDLL","comment":"Returns the name of the imported DLL.","params":[],"throws":[],"return":{"type_long":"java.lang.String","comment":"the name of the imported DLL","type_short":"String"}},{"javadoc":"Returns the name of the imported symbol.\n@return the name of the imported symbol","static":false,"name":"getName","comment":"Returns the name of the imported symbol.","params":[],"throws":[],"return":{"type_long":"java.lang.String","comment":"the name of the imported symbol","type_short":"String"}},{"javadoc":"Returns true if this is a bound import.\n@return true if this is a bound import","static":false,"name":"isBound","comment":"Returns true if this is a bound import.","params":[],"throws":[],"return":{"type_long":"boolean","comment":"true if this is a bound import","type_short":"boolean"}}],"name":"ImportInfo","comment":"","fields":[{"type_long":"int","javadoc":"","static":false,"name":"address","comment":"","type_short":"int","constant_value":null},{"type_long":"java.lang.String","javadoc":"","static":false,"name":"comment","comment":"","type_short":"String","constant_value":null},{"type_long":"java.lang.String","javadoc":"","static":false,"name":"dll","comment":"","type_short":"String","constant_value":null},{"type_long":"java.lang.String","javadoc":"","static":false,"name":"name","comment":"","type_short":"String","constant_value":null},{"type_long":"boolean","javadoc":"","static":false,"name":"isBound","comment":"","type_short":"boolean","constant_value":null}]}
